[null,{"name":"+","permissions":"ADMINISTRATOR","restriction":"1","actions":[{"storage":"2","varName":"Dni","changeType":"0","value":"serverVars(\"Dni\") + 1","name":"Control Variable"},{"channel":"6","varName":"","message":"Coś się pomyliło i trzeba było dodać jeden dzień :c > **${serverVars(\"Dni\")}**","storage":"0","varName2":"","name":"Send Message"},{"gameName":"Do Wakacji > ${serverVars(\"Dni\")}","gameLink":"","name":"Set Bot Game"}]},{"name":"-","permissions":"ADMINISTRATOR","restriction":"1","actions":[{"storage":"2","varName":"Dni","changeType":"0","value":"serverVars(\"Dni\") - 1","name":"Control Variable"},{"channel":"6","varName":"YukoCzat","message":"O jeden dzień roku szkolnego mniej! Pozostało > **${serverVars(\"Dni\")}** !","storage":"0","varName2":"","name":"Send Message"},{"gameName":"Do Wakacji > ${serverVars(\"Dni\")}","gameLink":"","name":"Set Bot Game"}]},{"name":"start","permissions":"ADMINISTRATOR","restriction":"1","actions":[{"info":"0","infoIndex":"1","storage":"2","varName":"Dni","name":"Store Command Params"},{"channel":"0","varName":"","message":"Start Licznika! Dni które pozostały do końca roku szkolnego > **${serverVars(\"Dni\")}**","storage":"0","varName2":"","name":"Send Message"},{"gameName":"Do Wakacji > ${serverVars(\"Dni\")}","gameLink":"","name":"Set Bot Game"},{"storage":"2","varName":"START","changeType":"0","value":"1","name":"Control Variable"}]},{"name":"wakacje","permissions":"NONE","restriction":"1","actions":[{"info":"0","infoIndex":"1","storage":"2","varName":"Dni","name":"Store Command Params"},{"channel":"0","varName":"","message":"${member} Do końca roku szkolnego zostało > **${serverVars(\"Dni\")}**","storage":"0","varName2":"","name":"Send Message"}]},{"name":"yukosiuko","permissions":"NONE","restriction":"1","actions":[{"channel":"0","varName":"","message":"* Meeeeeeeeeee * ","storage":"0","varName2":"","name":"Send Message"}]},{"name":"dedykacja","permissions":"NONE","restriction":"1","actions":[{"channel":"0","varName":"","message":"Bot napisany z dedykacja dla **Yuko** ^^ która jako pierwsza zaczęła odliczanie do wakacji na serwerze :3","storage":"0","varName2":"","name":"Send Message"}]},{"name":"komendy","permissions":"NONE","restriction":"1","actions":[{"channel":"0","varName":"","message":"Komendy Administracji\n- !- (-1 dzien)\n- !+ (+1 dzien)\nKomenda dostępna dla każdego:\n- !wakacje (pokazuje pozostałe Dni do wakacji)\n- !dedykacja (pokazuje dla kogo został bocik napisany :3)\n- !yukosiuko (MmMmEeEe)\n- !komendy (wyskakuje ta lista)","storage":"0","varName2":"","name":"Send Message"}]}]